pydeg/__init__.py
pydeg/normalizations.py
pydeg/pdd.py
pydeg/preworks.py
pydeg/stats.py
pydeg/utils.py
PyDEG-0.1.2.dist-info/LICENSE
PyDEG-0.1.2.dist-info/METADATA
PyDEG-0.1.2.dist-info/WHEEL
PyDEG-0.1.2.dist-info/top_level.txt
PyDEG-0.1.2.dist-info/RECORD
