Metadata-Version: 2.1
Name: PyDEG
Version: 0.1.2
Summary: A python implementation of differential expression analysis.
Author: labjc
Author-email: jakec26384@gmail.com
License: MIT
Requires-Python: >=3.9.0
License-File: LICENSE
